momositemaps/__init__.py
momositemaps-0.0.2.dist-info/METADATA
momositemaps-0.0.2.dist-info/WHEEL
momositemaps-0.0.2.dist-info/top_level.txt
momositemaps-0.0.2.dist-info/RECORD
